open_tunnels/__init__.py
open_tunnels/app.py
open_tunnels/cli.py
open_tunnels/downloader.py
open_tunnels/templates/dash.html
open_tunnels/templates/details.html
open_tunnels/templates/tunnels.html
open_tunnels-6.2.2.dist-info/METADATA
open_tunnels-6.2.2.dist-info/WHEEL
open_tunnels-6.2.2.dist-info/top_level.txt
open_tunnels-6.2.2.dist-info/RECORD
